Base/CustomRequest.py
Base/NSEBase.py
Base/__init__.py
Derivatives/NSE.py
Derivatives/Sensibull.py
Derivatives/__init__.py
Fundamentals/BSE.py
Fundamentals/MoneyControl.py
Fundamentals/TickerTape.py
Fundamentals/__init__.py
Technical/NSE.py
Technical/__init__.py
Bharat_sm_data-3.0.0.dist-info/LICENSE
Bharat_sm_data-3.0.0.dist-info/METADATA
Bharat_sm_data-3.0.0.dist-info/WHEEL
Bharat_sm_data-3.0.0.dist-info/top_level.txt
Bharat_sm_data-3.0.0.dist-info/RECORD
