Metadata-Version: 2.2
Name: Bharat_sm_data
Version: 3.0.0
Summary: Bharat SM Data stands for Bharat(India) Stock Market Data.
Home-page: https://github.com/Sampad-Hegde/Bharat-SM-Data
Author: Sampad Hegde
Author-email: me@sampadhegde.in
License: Apache License 2.0
Project-URL: Documentation, https://bharat-sm-data.readthedocs.io/en/latest/
Classifier: License :: OSI Approved :: Apache Software License
Classifier: Programming Language :: Python :: 3.7
Classifier: Operating System :: OS Independent
Requires-Python: >=3.7
License-File: LICENSE
Requires-Dist: requests>=2.31.0
Requires-Dist: pandas>=2.0.3
Requires-Dist: pydash>=7.0.6
Requires-Dist: beautifulsoup4>=4.12.2
Requires-Dist: numpy>=1.25.2
Requires-Dist: html5lib>=1.1
Requires-Dist: lxml>=4.9.3
Provides-Extra: dev
Requires-Dist: twine>=4.0.2; extra == "dev"
Dynamic: author
Dynamic: author-email
Dynamic: classifier
Dynamic: description
Dynamic: description-content-type
Dynamic: home-page
Dynamic: license
Dynamic: project-url
Dynamic: provides-extra
Dynamic: requires-dist
Dynamic: requires-python
Dynamic: summary
